quickjs/__init__.py
quickjs/_quickjs.cpython-310-x86_64-linux-gnu.so
quickjs/quickjs.py
quickjs_cffi-0.1.3.dist-info/LICENSE
quickjs_cffi-0.1.3.dist-info/METADATA
quickjs_cffi-0.1.3.dist-info/WHEEL
quickjs_cffi-0.1.3.dist-info/entry_points.txt
quickjs_cffi-0.1.3.dist-info/RECORD
