Metadata-Version: 2.1
Name: quickjs-cffi
Version: 0.1.3
Summary: Python binding for QuickJS using CFFI
Home-page: https://github.com/tangledgroup/quickjs-cffi
License: MIT
Author: Marko Tasic
Author-email: mtasic85@gmail.com
Requires-Python: >=3.10,<4.0
Classifier: License :: OSI Approved :: MIT License
Classifier: Programming Language :: Python :: 3
Classifier: Programming Language :: Python :: 3.10
Classifier: Programming Language :: Python :: 3.11
Classifier: Programming Language :: Python :: 3.12
Classifier: Programming Language :: Python :: 3.13
Provides-Extra: tqdm
Requires-Dist: cffi (>=1.17.1,<2.0.0)
Requires-Dist: setuptools (>=75.3.0,<76.0.0)
Requires-Dist: tqdm (>=4.66.6,<5.0.0) ; extra == "tqdm"
Project-URL: Repository, https://github.com/tangledgroup/quickjs-cffi
